hspf/Masslink_Timeseries.csv
hspf/__init__.py
hspf/build_warehouse.py
hspf/hbn.py
hspf/hbn2.py
hspf/hbn_cy.c
hspf/hbn_cy.html
hspf/hbn_cy.pyx
hspf/helpers.py
hspf/hspfModel.py
hspf/reports.py
hspf/uci.py
hspf/validations.py
hspf/warehouse.py
hspf/wdm.py
hspf/wdmReader.py
hspf/bin/WinHSPFLt/WinHspfLt.exe
hspf/data/HSPFParameterRanges.csv
hspf/data/LandUseNames_Mappings.csv
hspf/data/ParseTable.csv
hspf/data/Timeseries Catalog/IMPLND/IQUAL.txt
hspf/data/Timeseries Catalog/IMPLND/IWATER.txt
hspf/data/Timeseries Catalog/IMPLND/IWTGAS.txt
hspf/data/Timeseries Catalog/IMPLND/SOLIDS.txt
hspf/data/Timeseries Catalog/PERLND/MSTLAY.txt
hspf/data/Timeseries Catalog/PERLND/PQUAL.txt
hspf/data/Timeseries Catalog/PERLND/PSTEMP.txt
hspf/data/Timeseries Catalog/PERLND/PWATER.txt
hspf/data/Timeseries Catalog/PERLND/PWATGAS.txt
hspf/data/Timeseries Catalog/PERLND/SEDMNT.txt
hspf/data/Timeseries Catalog/PERLND/SNOW.txt
hspf/data/Timeseries Catalog/RCHRES/CONS.txt
hspf/data/Timeseries Catalog/RCHRES/GQUAL.txt
hspf/data/Timeseries Catalog/RCHRES/HTRCH.txt
hspf/data/Timeseries Catalog/RCHRES/HYDR.txt
hspf/data/Timeseries Catalog/RCHRES/NUTRX.txt
hspf/data/Timeseries Catalog/RCHRES/OXRX.txt
hspf/data/Timeseries Catalog/RCHRES/PLANK.txt
hspf/data/Timeseries Catalog/RCHRES/SEDTRN.txt
hspf/parser/__init__.py
hspf/parser/graph.py
hspf/parser/parsers.py
hspf-2.1.1.dist-info/METADATA
hspf-2.1.1.dist-info/WHEEL
hspf-2.1.1.dist-info/RECORD
