Metadata-Version: 2.4
Name: hspf
Version: 2.1.1
Summary: Python package for downloading and running HSPF models
Project-URL: Homepage, https://github.com/mfratkin1/pyHSPF
Author-email: Mulu Fratkin <michael.fratkin@state.mn.us>
Maintainer-email: Mulu Fratkin <michael.fratkin@state.mn.us>
License-Expression: MIT
Keywords: HSPF,Hydrology
Classifier: Development Status :: 3 - Alpha
Classifier: Programming Language :: Python
Requires-Python: >=3.8
Requires-Dist: networkx
Requires-Dist: numba
Requires-Dist: numpy
Requires-Dist: pandas
Requires-Dist: pathlib
Requires-Dist: requests
Requires-Dist: tables
